[{"latest.cost.tuition.in_state": null, "latest.cost.tuition.out_of_state": null, "latest.student.size": 174, "latest.earnings.6_yrs_after_entry.median": 32854, "latest.admissions.test_requirements": null, "latest.admissions.admission_rate.consumer_rate": 1, "latest.academics.program.degree.computer": 0, "latest.academics.program_percentage.computer": 0, "latest.admissions.sat_scores.25th_percentile.critical_reading": null, "latest.admissions.sat_scores.75th_percentile.critical_reading": null, "latest.admissions.sat_scores.25th_percentile.math": null, "latest.admissions.sat_scores.75th_percentile.math": null, "latest.admissions.sat_scores.25th_percentile.writing": null, "latest.admissions.sat_scores.75th_percentile.writing": null, "latest.admissions.sat_scores.midpoint.critical_reading": null, "latest.admissions.sat_scores.midpoint.math": null, "latest.admissions.sat_scores.midpoint.writing": null, "latest.admissions.sat_scores.average.overall": null, "latest.admissions.sat_scores.average.by_ope_id": null, "school.name": "Carrington College-Ontario", "school.city": "Ontario", "school.state": "CA", "school.school_url": "https://carrington.edu/", "school.locale": 12, "school.online_only": 0, "school.main_campus": 0}, {"latest.cost.tuition.in_state": null, "latest.cost.tuition.out_of_state": null, "latest.student.size": 121, "latest.earnings.6_yrs_after_entry.median": 30101, "latest.admissions.test_requirements": null, "latest.admissions.admission_rate.consumer_rate": 1, "latest.academics.program.degree.computer": 0, "latest.academics.program_percentage.computer": 0, "latest.admissions.sat_scores.25th_percentile.critical_reading": null, "latest.admissions.sat_scores.75th_percentile.critical_reading": null, "latest.admissions.sat_scores.25th_percentile.math": null, "latest.admissions.sat_scores.75th_percentile.math": null, "latest.admissions.sat_scores.25th_percentile.writing": null, "latest.admissions.sat_scores.75th_percentile.writing": null, "latest.admissions.sat_scores.midpoint.critical_reading": null, "latest.admissions.sat_scores.midpoint.math": null, "latest.admissions.sat_scores.midpoint.writing": null, "latest.admissions.sat_scores.average.overall": null, "latest.admissions.sat_scores.average.by_ope_id": null, "school.name": "North-West College-Pomona", "school.city": "Pomona", "school.state": "CA", "school.school_url": "www.north-westcollege.edu/", "school.locale": 21, "school.online_only": 0, "school.main_campus": 1}, {"latest.cost.tuition.in_state": 54774, "latest.cost.tuition.out_of_state": 54774, "latest.student.size": 1462, "latest.earnings.6_yrs_after_entry.median": 44630, "latest.admissions.test_requirements": 3, "latest.admissions.admission_rate.consumer_rate": 0.0862, "latest.academics.program.degree.computer": 1, "latest.academics.program_percentage.computer": 0.084, "latest.admissions.sat_scores.25th_percentile.critical_reading": null, "latest.admissions.sat_scores.75th_percentile.critical_reading": null, "latest.admissions.sat_scores.25th_percentile.math": null, "latest.admissions.sat_scores.75th_percentile.math": null, "latest.admissions.sat_scores.25th_percentile.writing": 680, "latest.admissions.sat_scores.75th_percentile.writing": 770, "latest.admissions.sat_scores.midpoint.critical_reading": null, "latest.admissions.sat_scores.midpoint.math": null, "latest.admissions.sat_scores.midpoint.writing": 725, "latest.admissions.sat_scores.average.overall": null, "latest.admissions.sat_scores.average.by_ope_id": null, "school.name": "Pomona College", "school.city": "Claremont", "school.state": "CA", "school.school_url": "www.pomona.edu/", "school.locale": 21, "school.online_only": 0, "school.main_campus": 1}]